saliency/__init__.py
saliency/core/__init__.py
saliency/core/base.py
saliency/core/base_test.py
saliency/core/blur_ig.py
saliency/core/blur_ig_test.py
saliency/core/grad_cam.py
saliency/core/grad_cam_test.py
saliency/core/gradients.py
saliency/core/gradients_test.py
saliency/core/guided_ig.py
saliency/core/guided_ig_test.py
saliency/core/integrated_gradients.py
saliency/core/integrated_gradients_test.py
saliency/core/occlusion.py
saliency/core/occlusion_test.py
saliency/core/visualization.py
saliency/core/xrai.py
saliency/core/xrai_test.py
saliency/metrics/__init__.py
saliency/metrics/pic.py
saliency/metrics/pic_test.py
saliency/tf1/__init__.py
saliency/tf1/base.py
saliency/tf1/base_test.py
saliency/tf1/blur_ig.py
saliency/tf1/blur_ig_test.py
saliency/tf1/grad_cam.py
saliency/tf1/grad_cam_test.py
saliency/tf1/gradients.py
saliency/tf1/gradients_test.py
saliency/tf1/guided_backprop.py
saliency/tf1/guided_ig.py
saliency/tf1/guided_ig_test.py
saliency/tf1/integrated_gradients.py
saliency/tf1/integrated_gradients_test.py
saliency/tf1/occlusion.py
saliency/tf1/occlusion_test.py
saliency/tf1/utils.py
saliency/tf1/utils_test.py
saliency/tf1/visualization.py
saliency/tf1/xrai.py
saliency/tf1/xrai_test.py
saliency-0.2.1.dist-info/LICENSE
saliency-0.2.1.dist-info/METADATA
saliency-0.2.1.dist-info/WHEEL
saliency-0.2.1.dist-info/top_level.txt
saliency-0.2.1.dist-info/RECORD
