Metadata-Version: 2.1
Name: saliency
Version: 0.2.1
Summary: Framework-agnostic saliency methods
Home-page: https://github.com/pair-code/saliency
Author: The saliency authors
Author-email: tf-saliency-dev@google.com
License: Apache 2.0
Keywords: saliency mask neural network deep learning
Classifier: Development Status :: 4 - Beta
Classifier: Intended Audience :: Developers
Classifier: Programming Language :: Python :: 3
Classifier: Programming Language :: Python :: 3.7
Classifier: Programming Language :: Python :: 3.8
Classifier: Programming Language :: Python :: 3.9
License-File: LICENSE
Requires-Dist: numpy
Requires-Dist: scikit-image
Provides-Extra: full
Requires-Dist: tensorflow >=1.15 ; extra == 'full'
Provides-Extra: tf1
Requires-Dist: tensorflow >=1.15 ; extra == 'tf1'
